kapla/__init__.py
kapla/services/__init__.py
kapla/services/__main__.py
kapla/services/application.py
kapla/services/backends/__init__.py
kapla/services/backends/nats/__init__.py
kapla/services/broker.py
kapla/services/concurrency.py
kapla/services/config.py
kapla/services/defaults.py
kapla/services/dependencies.py
kapla/services/errors.py
kapla/services/factory.py
kapla/services/headers.py
kapla/services/io.py
kapla/services/listeners.py
kapla/services/middlewares/__init__.py
kapla/services/middlewares/broker.py
kapla/services/middlewares/compression/__init__.py
kapla/services/middlewares/compression/brotli.py
kapla/services/middlewares/errors.py
kapla/services/middlewares/responses.py
kapla/services/middlewares/time/__init__.py
kapla/services/middlewares/time/publish.py
kapla/services/middlewares/time/request.py
kapla/services/middlewares/time/subscribe.py
kapla/services/middlewares/timeout.py
kapla/services/protocol.py
kapla/services/py.typed
kapla/services/requests.py
kapla/services/responses.py
kapla/services/router.py
kapla/services/senders.py
kapla/services/testing/__init__.py
kapla/services/testing/client.py
kapla/services/testing/sender.py
kapla/services/utils/__init__.py
kapla/services/utils/imports.py
kapla/services/utils/normalize.py
kapla/services/utils/subjects.py
kapla/services/validation.py
kapla_services-0.1.0.dist-info/WHEEL
kapla_services-0.1.0.dist-info/METADATA
kapla_services-0.1.0.dist-info/RECORD
