Metadata-Version: 2.1
Name: kapla-services
Version: 0.1.0
Summary: 
Author: charbonnierg
Author-email: guillaume.charbonnier@araymond.com
Requires-Python: >=3.8,<4.0
Classifier: Programming Language :: Python :: 3
Classifier: Programming Language :: Python :: 3.10
Classifier: Programming Language :: Python :: 3.8
Classifier: Programming Language :: Python :: 3.9
Requires-Dist: Brotli (>=1.0.9,<2.0.0)
Requires-Dist: anyio (>=3.4.0,<4.0.0)
Requires-Dist: nats-py (>=2.0.0-rc.5,<3.0.0)
Requires-Dist: pydantic (>=1.8.2,<2.0.0)
